switcherlabs/__init__.py
switcherlabs/http_client.py
switcherlabs/version.py
switcherlabs-0.1.1.dist-info/LICENSE
switcherlabs-0.1.1.dist-info/METADATA
switcherlabs-0.1.1.dist-info/WHEEL
switcherlabs-0.1.1.dist-info/top_level.txt
switcherlabs-0.1.1.dist-info/RECORD
