Metadata-Version: 2.1
Name: switcherlabs
Version: 0.1.1
Summary: Python SDK for SwitcherLabs
Home-page: https://github.com/switcherlabs/switcherlabs-python
Author: SwitcherLabs
Author-email: support@switcherlabs.com
License: MIT
Keywords: switcherslabs api feature-flags
Platform: UNKNOWN
Requires-Python: !=3.0.*, !=3.1.*, !=3.2.*, !=3.3.*
Requires-Dist: requests[security] (>=2.20) ; python_version < "3.0"
Requires-Dist: requests (>=2.20) ; python_version >= "3.0"
